opsys_cart_controller/__init__.py
opsys_cart_controller/cart_abstract.py
opsys_cart_controller/cart_controller.py
opsys_cart_controller/cart/__init__.py
opsys_cart_controller/cart/configs.py
opsys_cart_controller/cart/laser_distance.py
opsys_cart_controller/cart/motor_control.py
opsys_cart_controller/cart/ps_params.py
opsys_cart_controller-0.0.5.dist-info/LICENSE
opsys_cart_controller-0.0.5.dist-info/METADATA
opsys_cart_controller-0.0.5.dist-info/WHEEL
opsys_cart_controller-0.0.5.dist-info/top_level.txt
opsys_cart_controller-0.0.5.dist-info/RECORD
