Metadata-Version: 2.1
Name: opsys-cart-controller
Version: 0.0.5
Summary: python package for cart moving on rail control
Home-page: https://bitbucket.org/opsys_tech/opsys-cart-controller/src/master/
Download-URL: https://bitbucket.org/opsys_tech/opsys-cart-controller/src/master/
Author: dmitry.borovensky
Author-email: dmitry.borovensky@opsys-tech.com
License-File: LICENSE
